app/Main.py
app/__init__.py
windows_state_saver-0.0.11.dist-info/LICENSE.TXT
windows_state_saver-0.0.11.dist-info/METADATA
windows_state_saver-0.0.11.dist-info/WHEEL
windows_state_saver-0.0.11.dist-info/entry_points.txt
windows_state_saver-0.0.11.dist-info/top_level.txt
windows_state_saver-0.0.11.dist-info/RECORD
