Metadata-Version: 2.1
Name: windows-state-saver
Version: 0.0.11
Summary: Saves the current state of a Windows laptop and then reopen it.
Home-page: https://github.com/rishi-2893/Windows-State-Saver
Author: Rishi Patel
Author-email: rptl2803@gmail.com
License: MIT
Platform: UNKNOWN
Classifier: Intended Audience :: Developers
Classifier: Programming Language :: Python :: 3
Classifier: Operating System :: Microsoft :: Windows
License-File: LICENSE.TXT
Requires-Dist: importlib-resources
